aiowallhaven/__init__.py
aiowallhaven/api.py
aiowallhaven/api_exception_reasons.py
aiowallhaven/api_tests.py
aiowallhaven-0.0.4.dist-info/LICENSE.txt
aiowallhaven-0.0.4.dist-info/METADATA
aiowallhaven-0.0.4.dist-info/WHEEL
aiowallhaven-0.0.4.dist-info/top_level.txt
aiowallhaven-0.0.4.dist-info/RECORD
