Metadata-Version: 2.1
Name: aiowallhaven
Version: 0.0.4
Summary: Async wrapper for Wallhaven's API
Home-page: https://github.com/itsuchur/aiowallhaven
Download-URL: https://github.com/itsuchur/aiowallhaven/archive/refs/tags/0.0.3.tar.gz
Author: Dmitrii Efimov
Author-email: efimov.1992@outlook.com
License: MIT
Classifier: Programming Language :: Python :: 3 :: Only
Classifier: Programming Language :: Python :: 3.10
Classifier: License :: OSI Approved :: MIT License
Classifier: Operating System :: OS Independent
Requires-Python: >=3.10.0
License-File: LICENSE.txt
